{"nodes":[{"pos":[12,52],"content":"hash_set::end (STL-CLR) | Microsoft Docs","needQuote":false,"needEscape":true,"nodes":[{"content":"hash_set::end (STL-CLR) | Microsoft Docs","pos":[0,40]}]},{"content":"hash_set::end (STL/CLR)","pos":[626,649]},{"content":"Designates the end of the controlled sequence.","pos":[650,696]},{"content":"Syntax","pos":[705,711]},{"content":"Remarks","pos":[753,760]},{"content":"The member function returns a bidirectional iterator that points just beyond the end of the controlled sequence.","pos":[764,876]},{"content":"You use it to obtain an iterator that designates the end of the controlled sequence; its status doesn not change if the length of the controlled sequence changes.","pos":[877,1039]},{"content":"Example","pos":[1048,1055]},{"content":"Requirements","pos":[1803,1815]},{"pos":[1819,1849],"content":"<bpt id=\"p1\">**</bpt>Header:<ept id=\"p1\">**</ept> <ph id=\"ph1\">\\&lt;</ph>cliext/hash_set&gt;","source":"**Header:** \\<cliext/hash_set>"},{"pos":[1856,1877],"content":"<bpt id=\"p1\">**</bpt>Namespace:<ept id=\"p1\">**</ept> cliext","source":"**Namespace:** cliext"},{"content":"See Also","pos":[1886,1894]},{"content":"hash_set (STL/CLR)","pos":[1899,1917]},{"content":"hash_set::begin (STL/CLR)","pos":[1955,1980]}],"content":"---\ntitle: \"hash_set::end (STL-CLR) | Microsoft Docs\"\nms.custom: \"\"\nms.date: \"11/04/2016\"\nms.reviewer: \"\"\nms.suite: \"\"\nms.technology: \n  - \"devlang-cpp\"\nms.tgt_pltfrm: \"\"\nms.topic: \"reference\"\nf1_keywords: \n  - \"cliext::hash_set::end\"\ndev_langs: \n  - \"C++\"\nhelpviewer_keywords: \n  - \"end member [STL/CLR]\"\nms.assetid: 957de04e-fdc1-4295-ba25-8b0ad1ea97de\ncaps.latest.revision: 15\nauthor: \"mikeblome\"\nms.author: \"mblome\"\nmanager: \"ghogen\"\ntranslation.priority.ht: \n  - \"cs-cz\"\n  - \"de-de\"\n  - \"es-es\"\n  - \"fr-fr\"\n  - \"it-it\"\n  - \"ja-jp\"\n  - \"ko-kr\"\n  - \"pl-pl\"\n  - \"pt-br\"\n  - \"ru-ru\"\n  - \"tr-tr\"\n  - \"zh-cn\"\n  - \"zh-tw\"\n---\n# hash_set::end (STL/CLR)\nDesignates the end of the controlled sequence.  \n  \n## Syntax  \n  \n```  \niterator end();  \n```  \n  \n## Remarks  \n The member function returns a bidirectional iterator that points just beyond the end of the controlled sequence. You use it to obtain an iterator that designates the end of the controlled sequence; its status doesn not change if the length of the controlled sequence changes.  \n  \n## Example  \n  \n```  \n// cliext_hash_set_end.cpp   \n// compile with: /clr   \n#include <cliext/hash_set>   \n  \ntypedef cliext::hash_set<wchar_t> Myhash_set;   \nint main()   \n    {   \n    Myhash_set c1;   \n    c1.insert(L'a');   \n    c1.insert(L'b');   \n    c1.insert(L'c');   \n  \n// display initial contents \" a b c\"   \n    for each (wchar_t elem in c1)   \n        System::Console::Write(\" {0}\", elem);   \n    System::Console::WriteLine();   \n  \n// inspect last two items   \n    Myhash_set::iterator it = c1.end();   \n    --it;   \n    System::Console::WriteLine(\"*-- --end() = {0}\", *--it);   \n    System::Console::WriteLine(\"*--end() = {0}\", *++it);   \n    return (0);   \n    }  \n  \n```  \n  \n```Output  \n a b c  \n*-- --end() = b  \n*--end() = c  \n```  \n  \n## Requirements  \n **Header:** \\<cliext/hash_set>  \n  \n **Namespace:** cliext  \n  \n## See Also  \n [hash_set (STL/CLR)](../dotnet/hash-set-stl-clr.md)   \n [hash_set::begin (STL/CLR)](../dotnet/hash-set-begin-stl-clr.md)"}