{"nodes":[{"pos":[12,54],"content":"operation_timed_out Class | Microsoft Docs","needQuote":false,"needEscape":true,"nodes":[{"content":"operation_timed_out Class | Microsoft Docs","pos":[0,42]}]},{"content":"operation_timed_out Class","pos":[649,674]},{"content":"This class describes an exception thrown when an operation has timed out.","pos":[675,748]},{"content":"Syntax","pos":[757,763]},{"content":"Members","pos":[836,843]},{"content":"Public Constructors","pos":[853,872]},{"content":"Name","pos":[879,883]},{"content":"Description","pos":[884,895]},{"content":"operation_timed_out::operation_timed_out Constructor","pos":[934,986]},{"content":"Overloaded.","pos":[995,1006]},{"content":"Constructs an <ph id=\"ph1\">`operation_timed_out`</ph> object.","pos":[1007,1050],"source":" Constructs an `operation_timed_out` object."},{"content":"Inheritance Hierarchy","pos":[1060,1081]},{"content":"Requirements","pos":[1133,1145]},{"pos":[1149,1169],"content":"<bpt id=\"p1\">**</bpt>Header:<ept id=\"p1\">**</ept> concrt.h","source":"**Header:** concrt.h"},{"pos":[1176,1202],"content":"<bpt id=\"p1\">**</bpt>Namespace:<ept id=\"p1\">**</ept> concurrency","source":"**Namespace:** concurrency"},{"pos":[1233,1285],"content":"operation_timed_out::operation_timed_out Constructor"},{"pos":[1289,1332],"content":"Constructs an <ph id=\"ph1\">`operation_timed_out`</ph> object.","source":"Constructs an `operation_timed_out` object."},{"content":"Parameters","pos":[1462,1472]},{"content":"A descriptive message of the error.","pos":[1490,1525]},{"content":"See Also","pos":[1534,1542]},{"content":"concurrency Namespace","pos":[1547,1568]}],"content":"---\ntitle: \"operation_timed_out Class | Microsoft Docs\"\nms.custom: \"\"\nms.date: \"11/04/2016\"\nms.reviewer: \"\"\nms.suite: \"\"\nms.technology: \n  - \"devlang-cpp\"\nms.tgt_pltfrm: \"\"\nms.topic: \"article\"\nf1_keywords: \n  - \"concrt/concurrency::operation_timed_out\"\ndev_langs: \n  - \"C++\"\nhelpviewer_keywords: \n  - \"operation_timed_out class\"\nms.assetid: 963efe1d-a6e0-477c-9a70-d93d8412c897\ncaps.latest.revision: 19\nauthor: \"mikeblome\"\nms.author: \"mblome\"\nmanager: \"ghogen\"\ntranslation.priority.ht: \n  - \"cs-cz\"\n  - \"de-de\"\n  - \"es-es\"\n  - \"fr-fr\"\n  - \"it-it\"\n  - \"ja-jp\"\n  - \"ko-kr\"\n  - \"pl-pl\"\n  - \"pt-br\"\n  - \"ru-ru\"\n  - \"tr-tr\"\n  - \"zh-cn\"\n  - \"zh-tw\"\n---\n# operation_timed_out Class\nThis class describes an exception thrown when an operation has timed out.  \n  \n## Syntax  \n  \n```\nclass operation_timed_out : public std::exception;\n```  \n  \n## Members  \n  \n### Public Constructors  \n  \n|Name|Description|  \n|----------|-----------------|  \n|[operation_timed_out::operation_timed_out Constructor](#ctor)|Overloaded. Constructs an `operation_timed_out` object.|  \n  \n## Inheritance Hierarchy  \n `exception`  \n  \n `operation_timed_out`  \n  \n## Requirements  \n **Header:** concrt.h  \n  \n **Namespace:** concurrency  \n  \n##  <a name=\"ctor\"></a>  operation_timed_out::operation_timed_out Constructor  \n Constructs an `operation_timed_out` object.  \n  \n```\nexplicit _CRTIMP operation_timed_out(_In_z_ const char* _Message) throw();\n\noperation_timed_out() throw();\n```  \n  \n### Parameters  \n `_Message`  \n A descriptive message of the error.  \n  \n## See Also  \n [concurrency Namespace](concurrency-namespace.md)\n"}