{"nodes":[{"pos":[12,56],"content":"HandleT::operator= Operator | Microsoft Docs","needQuote":false,"needEscape":true,"nodes":[{"content":"HandleT::operator= Operator | Microsoft Docs","pos":[0,44]}]},{"content":"HandleT::operator= Operator","pos":[689,716]},{"content":"Moves the value of the specified HandleT object to the current HandleT object.","pos":[717,795]},{"content":"Syntax","pos":[804,810]},{"content":"Parameters","pos":[888,898]},{"content":"An rvalue-reference to a handle.","pos":[909,941]},{"content":"Return Value","pos":[950,962]},{"content":"A reference to the current HandleT object.","pos":[966,1008]},{"content":"Remarks","pos":[1017,1024]},{"pos":[1028,1101],"content":"This operation invalidates the HandleT object specified by parameter <ph id=\"ph1\">`h`</ph>.","source":"This operation invalidates the HandleT object specified by parameter `h`."},{"content":"Requirements","pos":[1110,1122]},{"pos":[1126,1152],"content":"<bpt id=\"p1\">**</bpt>Header:<ept id=\"p1\">**</ept> corewrappers.h","source":"**Header:** corewrappers.h"},{"pos":[1159,1198],"content":"<bpt id=\"p1\">**</bpt>Namespace:<ept id=\"p1\">**</ept> Microsoft::WRL::Wrappers","source":"**Namespace:** Microsoft::WRL::Wrappers"},{"content":"See Also","pos":[1207,1215]},{"content":"HandleT Class","pos":[1220,1233]}],"content":"---\ntitle: \"HandleT::operator= Operator | Microsoft Docs\"\nms.custom: \"\"\nms.date: \"11/04/2016\"\nms.reviewer: \"\"\nms.suite: \"\"\nms.technology: \n  - \"devlang-cpp\"\nms.tgt_pltfrm: \"\"\nms.topic: \"reference\"\nf1_keywords: \n  - \"corewrappers/Microsoft::WRL::Wrappers::HandleT::operator=\"\ndev_langs: \n  - \"C++\"\nhelpviewer_keywords: \n  - \"operator= operator\"\nms.assetid: 9e42dcca-30fa-4e8b-8954-802fd64a5595\ncaps.latest.revision: 3\nauthor: \"mikeblome\"\nms.author: \"mblome\"\nmanager: \"ghogen\"\ntranslation.priority.ht: \n  - \"de-de\"\n  - \"es-es\"\n  - \"fr-fr\"\n  - \"it-it\"\n  - \"ja-jp\"\n  - \"ko-kr\"\n  - \"ru-ru\"\n  - \"zh-cn\"\n  - \"zh-tw\"\ntranslation.priority.mt: \n  - \"cs-cz\"\n  - \"pl-pl\"\n  - \"pt-br\"\n  - \"tr-tr\"\n---\n# HandleT::operator= Operator\nMoves the value of the specified HandleT object to the current HandleT object.  \n  \n## Syntax  \n  \n```  \nHandleT& operator=(  \n   _Inout_ HandleT&& h  \n);  \n```  \n  \n#### Parameters  \n `h`  \n An rvalue-reference to a handle.  \n  \n## Return Value  \n A reference to the current HandleT object.  \n  \n## Remarks  \n This operation invalidates the HandleT object specified by parameter `h`.  \n  \n## Requirements  \n **Header:** corewrappers.h  \n  \n **Namespace:** Microsoft::WRL::Wrappers  \n  \n## See Also  \n [HandleT Class](../windows/handlet-class.md)"}