{"nodes":[{"pos":[12,63],"content":"Expression Evaluator Error CXX0025 | Microsoft Docs","needQuote":false,"needEscape":true,"nodes":[{"content":"Expression Evaluator Error CXX0025 | Microsoft Docs","pos":[0,51]}]},{"content":"Expression Evaluator Error CXX0025","pos":[629,663]},{"content":"operator needs struct/union","pos":[664,691]},{"pos":[698,830],"content":"An operator that takes an expression of <ph id=\"ph1\">`struct`</ph> or <bpt id=\"p1\">**</bpt>union<ept id=\"p1\">**</ept> type was applied to an expression that is not a <ph id=\"ph2\">`struct`</ph> or <bpt id=\"p2\">**</bpt>union<ept id=\"p2\">**</ept>.","source":"An operator that takes an expression of `struct` or **union** type was applied to an expression that is not a `struct` or **union**."},{"content":"Components of class, structure, or union variables must have a fully qualified name.","pos":[837,921]},{"content":"Components cannot be entered without full specification.","pos":[922,978]},{"content":"This error is identical to CAN0025.","pos":[985,1020]}],"content":"---\ntitle: \"Expression Evaluator Error CXX0025 | Microsoft Docs\"\nms.custom: \"\"\nms.date: \"11/04/2016\"\nms.reviewer: \"\"\nms.suite: \"\"\nms.technology: \n  - \"devlang-cpp\"\nms.tgt_pltfrm: \"\"\nms.topic: \"error-reference\"\nf1_keywords: \n  - \"CXX0025\"\ndev_langs: \n  - \"C++\"\nhelpviewer_keywords: \n  - \"CAN0025\"\n  - \"CXX0025\"\nms.assetid: 3e2fb541-63b3-46ac-9f93-3dadb253bcf6\ncaps.latest.revision: 6\nauthor: \"corob-msft\"\nms.author: \"corob\"\nmanager: \"ghogen\"\ntranslation.priority.ht: \n  - \"cs-cz\"\n  - \"de-de\"\n  - \"es-es\"\n  - \"fr-fr\"\n  - \"it-it\"\n  - \"ja-jp\"\n  - \"ko-kr\"\n  - \"pl-pl\"\n  - \"pt-br\"\n  - \"ru-ru\"\n  - \"tr-tr\"\n  - \"zh-cn\"\n  - \"zh-tw\"\n---\n# Expression Evaluator Error CXX0025\noperator needs struct/union  \n  \n An operator that takes an expression of `struct` or **union** type was applied to an expression that is not a `struct` or **union**.  \n  \n Components of class, structure, or union variables must have a fully qualified name. Components cannot be entered without full specification.  \n  \n This error is identical to CAN0025."}