{"nodes":[{"pos":[12,45],"content":"_CrtGetAllocHook | Microsoft Docs","needQuote":false,"needEscape":true,"nodes":[{"content":"_CrtGetAllocHook | Microsoft Docs","pos":[0,33]}]},{"pos":[982,998],"content":"_CrtGetAllocHook","linkify":"_CrtGetAllocHook","nodes":[{"content":"_CrtGetAllocHook","pos":[0,16]}]},{"content":"Retrieves the current client-defined allocation function for hooking into the C run-time debug memory allocation process (debug version only).","pos":[999,1141]},{"pos":[1150,1156],"content":"Syntax","linkify":"Syntax","nodes":[{"content":"Syntax","pos":[0,6]}]},{"pos":[1224,1236],"content":"Return Value","linkify":"Return Value","nodes":[{"content":"Return Value","pos":[0,12]}]},{"content":"Returns the currently defined allocation hook function.","pos":[1240,1295]},{"pos":[1304,1311],"content":"Remarks","linkify":"Remarks","nodes":[{"content":"Remarks","pos":[0,7]}]},{"pos":[1315,1456],"content":"<ph id=\"ph1\">`_CrtGetAllocHook`</ph> retrieves the current client-defined application hook function for the C run-time debug library memory allocation process.","source":"`_CrtGetAllocHook` retrieves the current client-defined application hook function for the C run-time debug library memory allocation process."},{"pos":[1463,1672],"content":"For more information about using other hook-capable run-time functions and writing your own client-defined hook functions, see <bpt id=\"p1\">[</bpt>Debug Hook Function Writing<ept id=\"p1\">](/visualstudio/debugger/debug-hook-function-writing)</ept>.","source":"For more information about using other hook-capable run-time functions and writing your own client-defined hook functions, see [Debug Hook Function Writing](/visualstudio/debugger/debug-hook-function-writing)."},{"pos":[1681,1693],"content":"Requirements","linkify":"Requirements","nodes":[{"content":"Requirements","pos":[0,12]}]},{"content":"Routine","pos":[1700,1707]},{"content":"Required header","pos":[1708,1723]},{"content":"<ph id=\"ph1\">\\&lt;</ph>crtdbg.h&gt;","pos":[1787,1798],"source":"\\<crtdbg.h>"},{"pos":[1806,1924],"content":"For more compatibility information, see <bpt id=\"p1\">[</bpt>Compatibility<ept id=\"p1\">](../../c-runtime-library/compatibility.md)</ept> in the Introduction.","source":"For more compatibility information, see [Compatibility](../../c-runtime-library/compatibility.md) in the Introduction."},{"pos":[1933,1942],"content":"Libraries","linkify":"Libraries","nodes":[{"content":"Libraries","pos":[0,9]}]},{"pos":[1946,2041],"content":"Debug versions of <bpt id=\"p1\">[</bpt>C run-time libraries<ept id=\"p1\">](../../c-runtime-library/crt-library-features.md)</ept> only.","source":"Debug versions of [C run-time libraries](../../c-runtime-library/crt-library-features.md) only."},{"pos":[2050,2075],"content":".NET Framework Equivalent","linkify":".NET Framework Equivalent","nodes":[{"content":".NET Framework Equivalent","pos":[0,25]}]},{"content":"Not applicable.","pos":[2079,2094]},{"content":"To call the standard C function, use <ph id=\"ph1\">`PInvoke`</ph>.","pos":[2095,2142],"source":" To call the standard C function, use `PInvoke`."},{"content":"For more information, see <bpt id=\"p1\">[</bpt>Platform Invoke Examples<ept id=\"p1\">](http://msdn.microsoft.com/Library/15926806-f0b7-487e-93a6-4e9367ec689f)</ept>.","pos":[2143,2268],"source":" For more information, see [Platform Invoke Examples](http://msdn.microsoft.com/Library/15926806-f0b7-487e-93a6-4e9367ec689f)."},{"pos":[2277,2285],"content":"See Also","linkify":"See Also","nodes":[{"content":"See Also","pos":[0,8]}]},{"content":"<bpt id=\"p1\">[</bpt>Debug Routines<ept id=\"p1\">](../../c-runtime-library/debug-routines.md)</ept><ph id=\"ph1\"> </ph>","pos":[2289,2349],"source":"[Debug Routines](../../c-runtime-library/debug-routines.md) "},{"content":"<bpt id=\"p1\"> [</bpt>_CrtSetAllocHook<ept id=\"p1\">](../../c-runtime-library/reference/crtsetallochook.md)</ept>","pos":[2352,2425],"source":" [_CrtSetAllocHook](../../c-runtime-library/reference/crtsetallochook.md)"}],"content":"---\ntitle: \"_CrtGetAllocHook | Microsoft Docs\"\nms.custom: \"\"\nms.date: \"11/04/2016\"\nms.reviewer: \"\"\nms.suite: \"\"\nms.technology: \n  - \"devlang-cpp\"\nms.tgt_pltfrm: \"\"\nms.topic: \"article\"\napiname: \n  - \"_CrtGetAllocHook\"\napilocation: \n  - \"msvcrt.dll\"\n  - \"msvcr80.dll\"\n  - \"msvcr90.dll\"\n  - \"msvcr100.dll\"\n  - \"msvcr100_clr0400.dll\"\n  - \"msvcr110.dll\"\n  - \"msvcr110_clr0400.dll\"\n  - \"msvcr120.dll\"\n  - \"msvcr120_clr0400.dll\"\n  - \"ucrtbase.dll\"\napitype: \"DLLExport\"\nf1_keywords: \n  - \"CrtGetAllocHook\"\n  - \"_CrtGetAllocHook\"\ndev_langs: \n  - \"C++\"\n  - \"C\"\nhelpviewer_keywords: \n  - \"_CrtGetAllocHook function\"\n  - \"CrtGetAllocHook function\"\nms.assetid: 036acf7c-547a-4b3f-a636-80451070d7ed\ncaps.latest.revision: 12\nauthor: \"corob-msft\"\nms.author: \"corob\"\nmanager: \"ghogen\"\ntranslation.priority.ht: \n  - \"de-de\"\n  - \"es-es\"\n  - \"fr-fr\"\n  - \"it-it\"\n  - \"ja-jp\"\n  - \"ko-kr\"\n  - \"ru-ru\"\n  - \"zh-cn\"\n  - \"zh-tw\"\ntranslation.priority.mt: \n  - \"cs-cz\"\n  - \"pl-pl\"\n  - \"pt-br\"\n  - \"tr-tr\"\n---\n# _CrtGetAllocHook\nRetrieves the current client-defined allocation function for hooking into the C run-time debug memory allocation process (debug version only).  \n  \n## Syntax  \n  \n```  \n_CRT_ALLOC_HOOK _CrtGetAllocHook( void );  \n```  \n  \n## Return Value  \n Returns the currently defined allocation hook function.  \n  \n## Remarks  \n `_CrtGetAllocHook` retrieves the current client-defined application hook function for the C run-time debug library memory allocation process.  \n  \n For more information about using other hook-capable run-time functions and writing your own client-defined hook functions, see [Debug Hook Function Writing](/visualstudio/debugger/debug-hook-function-writing).  \n  \n## Requirements  \n  \n|Routine|Required header|  \n|-------------|---------------------|  \n|`_CrtGetAllocHook`|\\<crtdbg.h>|  \n  \n For more compatibility information, see [Compatibility](../../c-runtime-library/compatibility.md) in the Introduction.  \n  \n## Libraries  \n Debug versions of [C run-time libraries](../../c-runtime-library/crt-library-features.md) only.  \n  \n## .NET Framework Equivalent  \n Not applicable. To call the standard C function, use `PInvoke`. For more information, see [Platform Invoke Examples](http://msdn.microsoft.com/Library/15926806-f0b7-487e-93a6-4e9367ec689f).  \n  \n## See Also  \n [Debug Routines](../../c-runtime-library/debug-routines.md)   \n [_CrtSetAllocHook](../../c-runtime-library/reference/crtsetallochook.md)"}